jarpcdantic_clients/__init__.py
jarpcdantic_clients/aiohttp_client.py
jarpcdantic_clients/cabbage_client.py
jarpcdantic_clients/requests_client.py
jarpcdantic_clients-1.0.3.dist-info/LICENSE
jarpcdantic_clients-1.0.3.dist-info/METADATA
jarpcdantic_clients-1.0.3.dist-info/WHEEL
jarpcdantic_clients-1.0.3.dist-info/top_level.txt
jarpcdantic_clients-1.0.3.dist-info/RECORD
