Metadata-Version: 2.2
Name: jarpcdantic_clients
Version: 1.0.3
Summary: Transports for JARPCdantic
Home-page: https://github.com/whiteapfel/jarpcdantic_clients/
Download-URL: https://pypi.org/project/jarpcdantic_clients/
Maintainer: WhiteApfel
Maintainer-email: white@pfel.ru
License: Mozilla Public License 2.0
Classifier: Development Status :: 3 - Alpha
Classifier: Programming Language :: Python :: 3.12
Classifier: Intended Audience :: Developers
Classifier: License :: OSI Approved :: Mozilla Public License 2.0 (MPL 2.0)
Classifier: Topic :: Utilities
Requires-Python: >=3.12
License-File: LICENSE
Provides-Extra: cabbagok
Provides-Extra: aiohttp
Requires-Dist: aiohttp~=3.9.5; extra == "aiohttp"
Provides-Extra: requests
Requires-Dist: requests==2.32.3; extra == "requests"
Provides-Extra: all
Requires-Dist: jarpcdantic~=0.1.15; extra == "all"
Requires-Dist: aioamqp~=0.15.0; extra == "all"
Requires-Dist: aiohttp~=3.9.5; extra == "all"
Requires-Dist: requests==2.32.3; extra == "all"
Dynamic: classifier
Dynamic: description
Dynamic: description-content-type
Dynamic: download-url
Dynamic: home-page
Dynamic: license
Dynamic: maintainer
Dynamic: maintainer-email
Dynamic: provides-extra
Dynamic: requires-python
Dynamic: summary
